explorerhat/__init__.py
explorerhat/ads1015.py
explorerhat/pins.py
ExplorerHAT-0.5.1.dist-info/LICENSE.txt
ExplorerHAT-0.5.1.dist-info/METADATA
ExplorerHAT-0.5.1.dist-info/WHEEL
ExplorerHAT-0.5.1.dist-info/top_level.txt
ExplorerHAT-0.5.1.dist-info/RECORD
