Metadata-Version: 2.1
Name: ExplorerHAT
Version: 0.5.1
Summary: A module to control the Explorer HAT Raspberry Pi Addon Board
Home-page: http://shop.pimoroni.com
Author: Philip Howard
Author-email: phil@pimoroni.com
License: MIT
Keywords: Raspberry Pi Explorer HAT
Platform: UNKNOWN
Classifier: Development Status :: 5 - Production/Stable
Classifier: Operating System :: POSIX :: Linux
Classifier: License :: OSI Approved :: MIT License
Classifier: Intended Audience :: Developers
Classifier: Programming Language :: Python :: 2.6
Classifier: Programming Language :: Python :: 2.7
Classifier: Programming Language :: Python :: 3
Classifier: Topic :: Software Development
Classifier: Topic :: System :: Hardware
Requires-Dist: cap1xxx (>=0.1.4)
